jupyterlab_ca_theme/__init__.py
jupyterlab_ca_theme/_version.py
jupyterlab_ca_theme/labextension/install.json
jupyterlab_ca_theme/labextension/package.json
jupyterlab_ca_theme/labextension/static/454.0eeb309aec21d97502cd.js
jupyterlab_ca_theme/labextension/static/462.f1cb72f6d018e27a2b9a.js
jupyterlab_ca_theme/labextension/static/remoteEntry.dd510bbdcde3e8ddaaa6.js
jupyterlab_ca_theme/labextension/static/style.js
jupyterlab_ca_theme/labextension/static/third-party-licenses.json
jupyterlab_ca_theme/labextension/themes/@composable/jupyterlab-ca-theme/index.css
jupyterlab_ca_theme/labextension/themes/@composable/jupyterlab-ca-theme/index.js
jupyterlab_ca_theme-0.3.1.data/data/share/jupyter/labextensions/@composable/jupyterlab-ca-theme/install.json
jupyterlab_ca_theme-0.3.1.data/data/share/jupyter/labextensions/@composable/jupyterlab-ca-theme/package.json
jupyterlab_ca_theme-0.3.1.data/data/share/jupyter/labextensions/@composable/jupyterlab-ca-theme/static/454.0eeb309aec21d97502cd.js
jupyterlab_ca_theme-0.3.1.data/data/share/jupyter/labextensions/@composable/jupyterlab-ca-theme/static/462.f1cb72f6d018e27a2b9a.js
jupyterlab_ca_theme-0.3.1.data/data/share/jupyter/labextensions/@composable/jupyterlab-ca-theme/static/remoteEntry.dd510bbdcde3e8ddaaa6.js
jupyterlab_ca_theme-0.3.1.data/data/share/jupyter/labextensions/@composable/jupyterlab-ca-theme/static/style.js
jupyterlab_ca_theme-0.3.1.data/data/share/jupyter/labextensions/@composable/jupyterlab-ca-theme/static/third-party-licenses.json
jupyterlab_ca_theme-0.3.1.data/data/share/jupyter/labextensions/@composable/jupyterlab-ca-theme/themes/@composable/jupyterlab-ca-theme/index.css
jupyterlab_ca_theme-0.3.1.data/data/share/jupyter/labextensions/@composable/jupyterlab-ca-theme/themes/@composable/jupyterlab-ca-theme/index.js
jupyterlab_ca_theme-0.3.1.dist-info/LICENSE
jupyterlab_ca_theme-0.3.1.dist-info/METADATA
jupyterlab_ca_theme-0.3.1.dist-info/WHEEL
jupyterlab_ca_theme-0.3.1.dist-info/top_level.txt
jupyterlab_ca_theme-0.3.1.dist-info/RECORD
