Metadata-Version: 2.1
Name: jupyterlab-ca-theme
Version: 0.3.1
Summary: This theme styles the integration of Jupyter Lab with Composable, known as DataLabs
Home-page: https://gitub.com/gdaccache/jupyterlabs_composable_theme
Author: George Daccache
License: BSD-3-Clause
Keywords: Jupyter,JupyterLab
Platform: Linux
Platform: Mac OS X
Platform: Windows
Classifier: License :: OSI Approved :: BSD License
Classifier: Programming Language :: Python
Classifier: Programming Language :: Python :: 3
Classifier: Programming Language :: Python :: 3.6
Classifier: Programming Language :: Python :: 3.7
Classifier: Programming Language :: Python :: 3.8
Classifier: Framework :: Jupyter
Classifier: Framework :: Jupyter :: JupyterLab :: 3
Classifier: Framework :: Jupyter :: JupyterLab :: Extensions
Classifier: Framework :: Jupyter :: JupyterLab :: Extensions :: Prebuilt
Classifier: Framework :: Jupyter :: JupyterLab :: Extensions :: Themes
Requires-Python: >=3.6
License-File: LICENSE
Requires-Dist: jupyterlab ==3.*,>=3.0.0
